LICENSE.md
README.md
gfftk/__init__.py
gfftk/__main__.py
gfftk/compare.py
gfftk/consensus.py
gfftk/convert.py
gfftk/fasta.py
gfftk/genbank.py
gfftk/gff.py
gfftk/go.py
gfftk/help_formatter.py
gfftk/interlap.py
gfftk/log.py
gfftk/paf.py
gfftk/rename.py
gfftk/sanitize.py
gfftk/sort.py
gfftk/stats.py
gfftk/utils.py
gfftk/data/go.obo.gz
gfftk-25.6.10.dist-info/METADATA
gfftk-25.6.10.dist-info/WHEEL
gfftk-25.6.10.dist-info/entry_points.txt
gfftk-25.6.10.dist-info/licenses/LICENSE.md
gfftk-25.6.10.dist-info/RECORD
