Metadata-Version: 2.4
Name: gfftk
Version: 25.6.10
Summary: GFFtk: genome annotation GFF3 tool kit
Project-URL: Homepage, https://github.com/nextgenusfs/gfftk
Project-URL: Repository, https://github.com/nextgenusfs/gfftk.git
Author-email: Jon Palmer <nextgenusfs@gmail.com>
License: BSD 2-Clause License
License-File: LICENSE.md
Keywords: annotation,bioinformatics,completeness,genome
Classifier: Development Status :: 4 - Beta
Classifier: Intended Audience :: Science/Research
Classifier: License :: OSI Approved :: BSD License
Classifier: Operating System :: Unix
Classifier: Programming Language :: Python
Classifier: Topic :: Scientific/Engineering :: Bio-Informatics
Requires-Python: >=3.7.0
Requires-Dist: gb-io>=0.3.2
Requires-Dist: natsort
Requires-Dist: numpy
Requires-Dist: requests
